LICENSE
MANIFEST.in
README.md
setup.cfg
setup.py
Hamburglar/__init__.py
Hamburglar/ham.conf
Hamburglar/rules/apple.yar
Hamburglar/rules/audio.yar
Hamburglar/rules/compressed.yar
Hamburglar/rules/crypto.yar
Hamburglar/rules/executables.yar
Hamburglar/rules/gif.yar
Hamburglar/rules/gps.yar
Hamburglar/rules/jpeg.yar
Hamburglar/rules/mem_dumps.yar
Hamburglar/rules/office.yar
Hamburglar/rules/pdf.yar
Hamburglar/rules/png.yar
Hamburglar/rules/skype.yar
Hamburglar/rules/sqlite.yar
Hamburglar/rules/vcard.yar
Hamburglar/rules/vector.yar
Hamburglar/rules/video.yar
Hamburglar/rules/vmware.yar
Hamburglar/rules/win_reg.yar
Hamburglar/utils/magic_sig_scraper.py
hamburglar/__init__.py
hamburglar/hamburglar.py
hamburglar.egg-info/PKG-INFO
hamburglar.egg-info/SOURCES.txt
hamburglar.egg-info/dependency_links.txt
hamburglar.egg-info/entry_points.txt
hamburglar.egg-info/requires.txt
hamburglar.egg-info/top_level.txt