Metadata-Version: 2.1
Name: hamburglar
Version: 1.0.1
Summary: command line tool to collect useful information from urls, directories, and files
Home-page: https://github.com/needmorecowbell/Hamburglar
Author: Adam Musciano
Author-email: amusciano@gmail.com
License: GNU
Keywords: Forensics,Static File Analysis
Platform: UNKNOWN
Classifier: Development Status :: 4 - Beta
Classifier: Intended Audience :: Information Technology
Classifier: Topic :: Software Development :: Build Tools
Classifier: License :: OSI Approved :: GNU General Public License v3 (GPLv3)
Classifier: Programming Language :: Python :: 3
Classifier: Programming Language :: Python :: 3.4
Classifier: Programming Language :: Python :: 3.5
Classifier: Programming Language :: Python :: 3.6
Classifier: Programming Language :: Python :: 3.7
